np_sound/__init__.py
np_sound/np_sound.py
np_sound-0.0.5.1.dist-info/METADATA
np_sound-0.0.5.1.dist-info/WHEEL
np_sound-0.0.5.1.dist-info/top_level.txt
np_sound-0.0.5.1.dist-info/RECORD
