Metadata-Version: 2.1
Name: np-sound
Version: 0.0.5.1
Summary: A NumPy-based sound library
Home-page: https://github.com/CharlesAverill/np_sound/
Author: Charles Averill
Author-email: charlesaverill20@gmail.com
License: UNKNOWN
Platform: UNKNOWN
Classifier: Programming Language :: Python :: 3
Classifier: License :: OSI Approved :: MIT License
Classifier: Operating System :: OS Independent
Requires-Dist: matplotlib
Requires-Dist: numpy
Requires-Dist: scipy
